LICENSE
MANIFEST.in
README.md
requirements-dev.txt
requirements.txt
setup.cfg
setup.py
pypi_version/__init__.py
pypi_version/cis.py
pypi_version/cli.py
pypi_version/config.py
pypi_version/constants.py
pypi_version/errors.py
pypi_version/main.py
pypi_version/utils.py
pypi_version.egg-info/PKG-INFO
pypi_version.egg-info/SOURCES.txt
pypi_version.egg-info/dependency_links.txt
pypi_version.egg-info/entry_points.txt
pypi_version.egg-info/requires.txt
pypi_version.egg-info/top_level.txt
tests/__init__.py
tests/conftest.py
tests/main/__init__.py
tests/main/test_package_version.py
tests/main/test_pull_request.py