Metadata-Version: 2.1
Name: pypi-version
Version: 0.2.0
Summary: Check if you haven't forgotten to bump the PyPi package version number before you merge a release pull request.
Home-page: https://github.com/dmytrostriletskyi/pypi-version
Author: Dmytro Striletskyi
Author-email: dmytro.striletskyi@gmail.com
License: MIT
Platform: UNKNOWN
Classifier: Operating System :: OS Independent
Classifier: Intended Audience :: Developers
Classifier: License :: OSI Approved :: MIT License
Classifier: Programming Language :: Python :: 3.4
Classifier: Programming Language :: Python :: 3.5
Classifier: Programming Language :: Python :: 3.6
Classifier: Programming Language :: Python :: 3.7
